{"ncaab.p.148672":{"name":"Jaelin Llewellyn","team":"Michigan Wolverines","stats":{},"current":false},"ncaab.p.153384":{"name":"Tray Jackson","team":"Michigan Wolverines","stats":{},"current":false},"ncaab.p.153931":{"name":"Olivier Nkamhoua","team":"Michigan Wolverines","stats":{},"current":false},"ncaab.p.159038":{"name":"Jace Howard","team":"Michigan Wolverines","stats":{},"current":false},"ncaab.p.159043":{"name":"Terrance Williams II","team":"Michigan Wolverines","stats":{},"current":false},"ncaab.p.159706":{"name":"Nimari Burnett","team":"Michigan Wolverines","stats":{},"current":false},"ncaab.p.162695":{"name":"Ian Burns","team":"Michigan Wolverines","stats":{},"current":false},"ncaab.p.162700":{"name":"Will Tschetter","team":"Michigan Wolverines","stats":{},"current":false},"ncaab.p.169376":{"name":"Dug McDaniel","team":"Michigan Wolverines","stats":{},"current":false},"ncaab.p.169380":{"name":"Youssef Khayat","team":"Michigan Wolverines","stats":{},"current":false},"ncaab.p.169384":{"name":"Tarris Reed Jr.","team":"Michigan Wolverines","stats":{},"current":false},"ncaab.p.169498":{"name":"Jackson Selvala","team":"Michigan Wolverines","stats":{},"current":false},"ncaab.p.169499":{"name":"Cooper Smith","team":"Michigan Wolverines","stats":{},"current":false},"ncaab.p.329967":{"name":"George Washington III","team":"Michigan Wolverines","stats":{},"current":false},"ncaab.p.329978":{"name":"Harrison Hochberg","team":"Michigan Wolverines","stats":{},"current":false},"ncaab.p.147136":{"name":"Xavier Johnson","team":"Indiana Hoosiers","stats":{},"current":false},"ncaab.p.152903":{"name":"Anthony Walker","team":"Indiana Hoosiers","stats":{},"current":false},"ncaab.p.159587":{"name":"Anthony Leal","team":"Indiana Hoosiers","stats":{},"current":false},"ncaab.p.159592":{"name":"Trey Galloway","team":"Indiana Hoosiers","stats":{},"current":false},"ncaab.p.163180":{"name":"Shaan Burke","team":"Indiana Hoosiers","stats":{},"current":false},"ncaab.p.163301":{"name":"Payton Sparks","team":"Indiana Hoosiers","stats":{},"current":false},"ncaab.p.168600":{"name":"Malik Reneau","team":"Indiana Hoosiers","stats":{},"current":false},"ncaab.p.168601":{"name":"Kaleb Banks","team":"Indiana Hoosiers","stats":{},"current":false},"ncaab.p.168602":{"name":"CJ Gunn","team":"Indiana Hoosiers","stats":{},"current":false},"ncaab.p.168971":{"name":"Kel'el Ware","team":"Indiana Hoosiers","stats":{},"current":false},"ncaab.p.205496":{"name":"Jordan Rayford","team":"Indiana Hoosiers","stats":{},"current":false},"ncaab.p.330155":{"name":"Gabe Cupps","team":"Indiana Hoosiers","stats":{},"current":false},"ncaab.p.330157":{"name":"James Goodis","team":"Indiana Hoosiers","stats":{},"current":false},"ncaab.p.330162":{"name":"Mackenzie Mgbako","team":"Indiana Hoosiers","stats":{},"current":false},"ncaab.p.330163":{"name":"Jackson Creel","team":"Indiana Hoosiers","stats":{},"current":false},"ncaab.p.330165":{"name":"Ian Stephens","team":"Indiana Hoosiers","stats":{},"current":false},"ncaab.p.330168":{"name":"Jakai Newton","team":"Indiana Hoosiers","stats":{},"current":false},"ncaab.p.153819":{"name":"Ben Krikke","team":"Iowa Hawkeyes","stats":{},"current":false},"ncaab.p.154372":{"name":"Patrick McCaffery","team":"Iowa Hawkeyes","stats":{},"current":false},"ncaab.p.158537":{"name":"Tony Perkins","team":"Iowa Hawkeyes","stats":{},"current":false},"ncaab.p.158733":{"name":"Even Brauns","team":"Iowa Hawkeyes","stats":{},"current":false},"ncaab.p.162631":{"name":"Payton Sandfort","team":"Iowa Hawkeyes","stats":{},"current":false},"ncaab.p.162634":{"name":"Riley Mulvey","team":"Iowa Hawkeyes","stats":{},"current":false},"ncaab.p.163242":{"name":"Carter Kingsbury","team":"Iowa Hawkeyes","stats":{},"current":false},"ncaab.p.163243":{"name":"Luc Laketa","team":"Iowa Hawkeyes","stats":{},"current":false},"ncaab.p.168618":{"name":"Josh Dix","team":"Iowa Hawkeyes","stats":{},"current":false},"ncaab.p.168619":{"name":"Dasonte Bowen","team":"Iowa Hawkeyes","stats":{},"current":false},"ncaab.p.330156":{"name":"Brock Harding","team":"Iowa Hawkeyes","stats":{},"current":false},"ncaab.p.330160":{"name":"Pryce Sandfort","team":"Iowa Hawkeyes","stats":{},"current":false},"ncaab.p.330161":{"name":"Ladji Dembele","team":"Iowa Hawkeyes","stats":{},"current":false},"ncaab.p.330167":{"name":"Owen Freeman","team":"Iowa Hawkeyes","stats":{},"current":false},"ncaab.p.331267":{"name":"Spencer Hutchison","team":"Iowa Hawkeyes","stats":{},"current":false},"ncaab.p.333429":{"name":"Jovone Cater","team":"Iowa Hawkeyes","stats":{},"current":false},"ncaab.p.152952":{"name":"Jack Wilson","team":"Minnesota Golden Gophers","stats":{},"current":false},"ncaab.p.154171":{"name":"Isaiah Ihnen","team":"Minnesota Golden Gophers","stats":{},"current":false},"ncaab.p.159343":{"name":"Dawson Garcia","team":"Minnesota Golden Gophers","stats":{},"current":false},"ncaab.p.162553":{"name":"Elijah Hawkins","team":"Minnesota Golden Gophers","stats":{},"current":false},"ncaab.p.162729":{"name":"Parker Fox","team":"Minnesota Golden Gophers","stats":{},"current":false},"ncaab.p.162732":{"name":"Jackson Purcell","team":"Minnesota Golden Gophers","stats":{},"current":false},"ncaab.p.163399":{"name":"Mike Mitchell Jr.","team":"Minnesota Golden Gophers","stats":{},"current":false},"ncaab.p.163526":{"name":"Will Ramberg","team":"Minnesota Golden Gophers","stats":{},"current":false},"ncaab.p.168799":{"name":"Joshua Ola-Joseph","team":"Minnesota Golden Gophers","stats":{},"current":false},"ncaab.p.168800":{"name":"Braeden Carrington","team":"Minnesota Golden Gophers","stats":{},"current":false},"ncaab.p.168801":{"name":"Kadyn Betts","team":"Minnesota Golden Gophers","stats":{},"current":false},"ncaab.p.168802":{"name":"Pharrel Payne","team":"Minnesota Golden Gophers","stats":{},"current":false},"ncaab.p.330175":{"name":"Cam Christie","team":"Minnesota Golden Gophers","stats":{},"current":false},"ncaab.p.330177":{"name":"Kris Keinys","team":"Minnesota Golden Gophers","stats":{},"current":false},"ncaab.p.330190":{"name":"Erick Reader","team":"Minnesota Golden Gophers","stats":{},"current":false},"ncaab.p.147591":{"name":"RayQuawndis Mitchell","team":"Penn State Nittany Lions","stats":{},"current":false},"ncaab.p.153747":{"name":"Leo O'Boyle","team":"Penn State Nittany Lions","stats":{},"current":false},"ncaab.p.155389":{"name":"Qudus Wahab","team":"Penn State Nittany Lions","stats":{},"current":false},"ncaab.p.159085":{"name":"Ace Baldwin Jr.","team":"Penn State Nittany Lions","stats":{},"current":false},"ncaab.p.159909":{"name":"Puff Johnson","team":"Penn State Nittany Lions","stats":{},"current":false},"ncaab.p.160171":{"name":"Andy Christos","team":"Penn State Nittany Lions","stats":{},"current":false},"ncaab.p.162711":{"name":"D'Marco Dunn","team":"Penn State Nittany Lions","stats":{},"current":false},"ncaab.p.163089":{"name":"Nick Kern Jr.","team":"Penn State Nittany Lions","stats":{},"current":false},"ncaab.p.163408":{"name":"Zach Hicks","team":"Penn State Nittany Lions","stats":{},"current":false},"ncaab.p.163624":{"name":"Dan Conlan","team":"Penn State Nittany Lions","stats":{},"current":false},"ncaab.p.168778":{"name":"Favour Aire","team":"Penn State Nittany Lions","stats":{},"current":false},"ncaab.p.168902":{"name":"Kanye Clary","team":"Penn State Nittany Lions","stats":{},"current":false},"ncaab.p.168904":{"name":"Jameel Brown","team":"Penn State Nittany Lions","stats":{},"current":false},"ncaab.p.168906":{"name":"Demetrius Lilley","team":"Penn State Nittany Lions","stats":{},"current":false},"ncaab.p.330213":{"name":"Bragi Gudmundsson","team":"Penn State Nittany Lions","stats":{},"current":false},"ncaab.p.153249":{"name":"Jahmir Young","team":"Maryland Terrapins","stats":{},"current":false},"ncaab.p.154152":{"name":"Donta Scott","team":"Maryland Terrapins","stats":{},"current":false},"ncaab.p.159591":{"name":"Jordan Geronimo","team":"Maryland Terrapins","stats":{},"current":false},"ncaab.p.159849":{"name":"Jahari Long","team":"Maryland Terrapins","stats":{},"current":false},"ncaab.p.162741":{"name":"Julian Reese","team":"Maryland Terrapins","stats":{},"current":false},"ncaab.p.168703":{"name":"Chance Stephens","team":"Maryland Terrapins","stats":{},"current":false},"ncaab.p.168749":{"name":"Noah Batchelor","team":"Maryland Terrapins","stats":{},"current":false},"ncaab.p.168750":{"name":"Caelum Swanton-Rodger","team":"Maryland Terrapins","stats":{},"current":false},"ncaab.p.300314":{"name":"Mady Traore","team":"Maryland Terrapins","stats":{},"current":false},"ncaab.p.330158":{"name":"Jahnathan Lamothe","team":"Maryland Terrapins","stats":{},"current":false},"ncaab.p.330176":{"name":"DeShawn Harris-Smith","team":"Maryland Terrapins","stats":{},"current":false},"ncaab.p.330180":{"name":"Braden Pierce","team":"Maryland Terrapins","stats":{},"current":false},"ncaab.p.330188":{"name":"Jamie Kaiser Jr.","team":"Maryland Terrapins","stats":{},"current":false},"ncaab.p.333426":{"name":"Lukas Sotell","team":"Maryland Terrapins","stats":{},"current":false},"ncaab.p.333427":{"name":"Ben Murphy","team":"Maryland Terrapins","stats":{},"current":false},"ncaab.p.152835":{"name":"Jamison Battle","team":"Ohio State Buckeyes","stats":{},"current":false},"ncaab.p.156424":{"name":"Dale Bonner","team":"Ohio State Buckeyes","stats":{},"current":false},"ncaab.p.159202":{"name":"Zed Key","team":"Ohio State Buckeyes","stats":{},"current":false},"ncaab.p.159330":{"name":"Owen Spencer","team":"Ohio State Buckeyes","stats":{},"current":false},"ncaab.p.162830":{"name":"Kalen Etzler","team":"Ohio State Buckeyes","stats":{},"current":false},"ncaab.p.168905":{"name":"Evan Mahaffey","team":"Ohio State Buckeyes","stats":{},"current":false},"ncaab.p.169390":{"name":"Roddy Gayle Jr.","team":"Ohio State Buckeyes","stats":{},"current":false},"ncaab.p.169391":{"name":"Bruce Thornton","team":"Ohio State Buckeyes","stats":{},"current":false},"ncaab.p.169399":{"name":"Bowen Hardman","team":"Ohio State Buckeyes","stats":{},"current":false},"ncaab.p.169403":{"name":"Felix Okpara","team":"Ohio State Buckeyes","stats":{},"current":false},"ncaab.p.169405":{"name":"Colby Baumann","team":"Ohio State Buckeyes","stats":{},"current":false},"ncaab.p.330173":{"name":"Devin Royal","team":"Ohio State Buckeyes","stats":{},"current":false},"ncaab.p.330183":{"name":"Taison Chatman","team":"Ohio State Buckeyes","stats":{},"current":false},"ncaab.p.330185":{"name":"Scotty Middleton","team":"Ohio State Buckeyes","stats":{},"current":false},"ncaab.p.330187":{"name":"Austin Parks","team":"Ohio State Buckeyes","stats":{},"current":false},"ncaab.p.153009":{"name":"Marcus Domask","team":"Illinois Fighting Illini","stats":{},"current":false},"ncaab.p.153612":{"name":"Quincy Guerrier","team":"Illinois Fighting Illini","stats":{},"current":false},"ncaab.p.153760":{"name":"Terrence Shannon Jr.","team":"Illinois Fighting Illini","stats":{},"current":false},"ncaab.p.158968":{"name":"Coleman Hawkins","team":"Illinois Fighting Illini","stats":{},"current":false},"ncaab.p.159693":{"name":"Max Williams","team":"Illinois Fighting Illini","stats":{},"current":false},"ncaab.p.160029":{"name":"Dain Dainja","team":"Illinois Fighting Illini","stats":{},"current":false},"ncaab.p.162556":{"name":"Luke Goode","team":"Illinois Fighting Illini","stats":{},"current":false},"ncaab.p.162978":{"name":"Keaton Kutcher","team":"Illinois Fighting Illini","stats":{},"current":false},"ncaab.p.163057":{"name":"Justin Harmon","team":"Illinois Fighting Illini","stats":{},"current":false},"ncaab.p.168594":{"name":"Sencire Harris","team":"Illinois Fighting Illini","stats":{},"current":false},"ncaab.p.168596":{"name":"Ty Rodgers","team":"Illinois Fighting Illini","stats":{},"current":false},"ncaab.p.300209":{"name":"AJ Redd","team":"Illinois Fighting Illini","stats":{},"current":false},"ncaab.p.300391":{"name":"Niccolo Moretti","team":"Illinois Fighting Illini","stats":{},"current":false},"ncaab.p.330154":{"name":"Dra Gibbs-Lawhorn","team":"Illinois Fighting Illini","stats":{},"current":false},"ncaab.p.330166":{"name":"Amani Hansberry","team":"Illinois Fighting Illini","stats":{},"current":false},"ncaab.p.153285":{"name":"Mason Gillis","team":"Purdue Boilermakers","stats":{},"current":false},"ncaab.p.154331":{"name":"Lance Jones","team":"Purdue Boilermakers","stats":{},"current":false},"ncaab.p.158686":{"name":"Zach Edey","team":"Purdue Boilermakers","stats":{},"current":false},"ncaab.p.158688":{"name":"Chase Martin","team":"Purdue Boilermakers","stats":{},"current":false},"ncaab.p.158693":{"name":"Ethan Morton","team":"Purdue Boilermakers","stats":{},"current":false},"ncaab.p.158694":{"name":"Carson Barrett","team":"Purdue Boilermakers","stats":{},"current":false},"ncaab.p.162781":{"name":"Brian Waddell","team":"Purdue Boilermakers","stats":{},"current":false},"ncaab.p.162783":{"name":"Trey Kaufman-Renn","team":"Purdue Boilermakers","stats":{},"current":false},"ncaab.p.162784":{"name":"Caleb Furst","team":"Purdue Boilermakers","stats":{},"current":false},"ncaab.p.168928":{"name":"Fletcher Loyer","team":"Purdue Boilermakers","stats":{},"current":false},"ncaab.p.168930":{"name":"Braden Smith","team":"Purdue Boilermakers","stats":{},"current":false},"ncaab.p.168931":{"name":"Camden Heide","team":"Purdue Boilermakers","stats":{},"current":false},"ncaab.p.168932":{"name":"Sam King","team":"Purdue Boilermakers","stats":{},"current":false},"ncaab.p.168933":{"name":"Will Berg","team":"Purdue Boilermakers","stats":{},"current":false},"ncaab.p.330206":{"name":"Josh Furst","team":"Purdue Boilermakers","stats":{},"current":false},"ncaab.p.330208":{"name":"Jace Rayl","team":"Purdue Boilermakers","stats":{},"current":false},"ncaab.p.330224":{"name":"Myles Colvin","team":"Purdue Boilermakers","stats":{},"current":false},"ncaab.p.153114":{"name":"Tyson Walker","team":"Michigan State Spartans","stats":{},"current":false},"ncaab.p.154163":{"name":"Malik Hall","team":"Michigan State Spartans","stats":{},"current":false},"ncaab.p.154165":{"name":"Steven Izzo","team":"Michigan State Spartans","stats":{},"current":false},"ncaab.p.159657":{"name":"Mady Sissoko","team":"Michigan State Spartans","stats":{},"current":false},"ncaab.p.159659":{"name":"Davis Smith","team":"Michigan State Spartans","stats":{},"current":false},"ncaab.p.159661":{"name":"A.J. Hoggard","team":"Michigan State Spartans","stats":{},"current":false},"ncaab.p.163289":{"name":"Jaden Akins","team":"Michigan State Spartans","stats":{},"current":false},"ncaab.p.169584":{"name":"Jaxon Kohler","team":"Michigan State Spartans","stats":{},"current":false},"ncaab.p.169585":{"name":"Tre Holloman","team":"Michigan State Spartans","stats":{},"current":false},"ncaab.p.169586":{"name":"Carson Cooper","team":"Michigan State Spartans","stats":{},"current":false},"ncaab.p.169587":{"name":"Nick Sanders","team":"Michigan State Spartans","stats":{},"current":false},"ncaab.p.331209":{"name":"Jeremy Fears Jr.","team":"Michigan State Spartans","stats":{},"current":false},"ncaab.p.331210":{"name":"Gehrig Normand","team":"Michigan State Spartans","stats":{},"current":false},"ncaab.p.331212":{"name":"Coen Carr","team":"Michigan State Spartans","stats":{},"current":false},"ncaab.p.331215":{"name":"Xavier Booker","team":"Michigan State Spartans","stats":{},"current":false},"ncaab.p.142167":{"name":"Austin Williams","team":"Rutgers Scarlet Knights","stats":{},"current":false},"ncaab.p.148259":{"name":"Aundre Hyatt","team":"Rutgers Scarlet Knights","stats":{},"current":false},"ncaab.p.153020":{"name":"Noah Fernandes","team":"Rutgers Scarlet Knights","stats":{},"current":false},"ncaab.p.157851":{"name":"Zach Hayn","team":"Rutgers Scarlet Knights","stats":{},"current":false},"ncaab.p.159065":{"name":"Oskar Palmquist","team":"Rutgers Scarlet Knights","stats":{},"current":false},"ncaab.p.159068":{"name":"Mawot Mag","team":"Rutgers Scarlet Knights","stats":{},"current":false},"ncaab.p.159072":{"name":"Clifford Omoruyi","team":"Rutgers Scarlet Knights","stats":{},"current":false},"ncaab.p.160075":{"name":"Jeremiah Williams","team":"Rutgers Scarlet Knights","stats":{},"current":false},"ncaab.p.160148":{"name":"Aiden Terry","team":"Rutgers Scarlet Knights","stats":{},"current":false},"ncaab.p.169007":{"name":"Derek Simpson","team":"Rutgers Scarlet Knights","stats":{},"current":false},"ncaab.p.169008":{"name":"Antwone Woolfolk","team":"Rutgers Scarlet Knights","stats":{},"current":false},"ncaab.p.169009":{"name":"Antonio Chol","team":"Rutgers Scarlet Knights","stats":{},"current":false},"ncaab.p.330196":{"name":"Daniel Vessey","team":"Rutgers Scarlet Knights","stats":{},"current":false},"ncaab.p.330204":{"name":"Emmanuel Ogbole","team":"Rutgers Scarlet Knights","stats":{},"current":false},"ncaab.p.330209":{"name":"Jacob Morales","team":"Rutgers Scarlet Knights","stats":{},"current":false},"ncaab.p.330212":{"name":"Jamichael Davis","team":"Rutgers Scarlet Knights","stats":{},"current":false},"ncaab.p.330221":{"name":"Gavin Griffiths","team":"Rutgers Scarlet Knights","stats":{},"current":false},"ncaab.p.153378":{"name":"Tyler Wahl","team":"Wisconsin Badgers","stats":{},"current":false},"ncaab.p.158787":{"name":"Carter Gilmore","team":"Wisconsin Badgers","stats":{},"current":false},"ncaab.p.158795":{"name":"Steven Crowl","team":"Wisconsin Badgers","stats":{},"current":false},"ncaab.p.158888":{"name":"Isaac Lindsey","team":"Wisconsin Badgers","stats":{},"current":false},"ncaab.p.159630":{"name":"Max Klesmit","team":"Wisconsin Badgers","stats":{},"current":false},"ncaab.p.162533":{"name":"Kamari McGee","team":"Wisconsin Badgers","stats":{},"current":false},"ncaab.p.163024":{"name":"Chris Hodges","team":"Wisconsin Badgers","stats":{},"current":false},"ncaab.p.163025":{"name":"Chucky Hepburn","team":"Wisconsin Badgers","stats":{},"current":false},"ncaab.p.163027":{"name":"Markus Ilver","team":"Wisconsin Badgers","stats":{},"current":false},"ncaab.p.169010":{"name":"AJ Storr","team":"Wisconsin Badgers","stats":{},"current":false},"ncaab.p.169307":{"name":"Connor Essegian","team":"Wisconsin Badgers","stats":{},"current":false},"ncaab.p.169309":{"name":"Luke Haertle","team":"Wisconsin Badgers","stats":{},"current":false},"ncaab.p.169312":{"name":"Isaac Gard","team":"Wisconsin Badgers","stats":{},"current":false},"ncaab.p.169313":{"name":"Ross Candelino","team":"Wisconsin Badgers","stats":{},"current":false},"ncaab.p.330200":{"name":"Jack Janicki","team":"Wisconsin Badgers","stats":{},"current":false},"ncaab.p.330201":{"name":"Gus Yalden","team":"Wisconsin Badgers","stats":{},"current":false},"ncaab.p.330203":{"name":"Nolan Winter","team":"Wisconsin Badgers","stats":{},"current":false},"ncaab.p.330219":{"name":"John Blackwell","team":"Wisconsin Badgers","stats":{},"current":false},"ncaab.p.147773":{"name":"Jarron Coleman","team":"Nebraska Cornhuskers","stats":{},"current":false},"ncaab.p.153022":{"name":"Juwan Gary","team":"Nebraska Cornhuskers","stats":{},"current":false},"ncaab.p.153254":{"name":"Brice Williams","team":"Nebraska Cornhuskers","stats":{},"current":false},"ncaab.p.153982":{"name":"Josiah Allick","team":"Nebraska Cornhuskers","stats":{},"current":false},"ncaab.p.154390":{"name":"Rienk Mast","team":"Nebraska Cornhuskers","stats":{},"current":false},"ncaab.p.158536":{"name":"Ahron Ulis","team":"Nebraska Cornhuskers","stats":{},"current":false},"ncaab.p.159445":{"name":"C.J. Wilcher","team":"Nebraska Cornhuskers","stats":{},"current":false},"ncaab.p.162668":{"name":"Sam Hoiberg","team":"Nebraska Cornhuskers","stats":{},"current":false},"ncaab.p.163555":{"name":"Keisei Tominaga","team":"Nebraska Cornhuskers","stats":{},"current":false},"ncaab.p.164155":{"name":"Jeffrey Grace III","team":"Nebraska Cornhuskers","stats":{},"current":false},"ncaab.p.168848":{"name":"Ramel Lloyd Jr.","team":"Nebraska Cornhuskers","stats":{},"current":false},"ncaab.p.168849":{"name":"Jamarques Lawrence","team":"Nebraska Cornhuskers","stats":{},"current":false},"ncaab.p.168850":{"name":"Cale Jacobsen","team":"Nebraska Cornhuskers","stats":{},"current":false},"ncaab.p.168851":{"name":"Henry Burt","team":"Nebraska Cornhuskers","stats":{},"current":false},"ncaab.p.169177":{"name":"Blaise Keita","team":"Nebraska Cornhuskers","stats":{},"current":false},"ncaab.p.329993":{"name":"Eli Rice","team":"Nebraska Cornhuskers","stats":{},"current":false},"ncaab.p.330005":{"name":"Matar Diop","team":"Nebraska Cornhuskers","stats":{},"current":false},"ncaab.p.147104":{"name":"Blake Preston","team":"Northwestern Wildcats","stats":{},"current":false},"ncaab.p.153169":{"name":"Boo Buie","team":"Northwestern Wildcats","stats":{},"current":false},"ncaab.p.155319":{"name":"Ryan Langborg","team":"Northwestern Wildcats","stats":{},"current":false},"ncaab.p.160142":{"name":"Ty Berry","team":"Northwestern Wildcats","stats":{},"current":false},"ncaab.p.160143":{"name":"Matthew Nicholson","team":"Northwestern Wildcats","stats":{},"current":false},"ncaab.p.162767":{"name":"Brooks Barnhizer","team":"Northwestern Wildcats","stats":{},"current":false},"ncaab.p.168525":{"name":"Justin Mullins","team":"Northwestern Wildcats","stats":{},"current":false},"ncaab.p.168909":{"name":"Nick Martinelli","team":"Northwestern Wildcats","stats":{},"current":false},"ncaab.p.168911":{"name":"Luke Hunger","team":"Northwestern Wildcats","stats":{},"current":false},"ncaab.p.168913":{"name":"Blake Smith","team":"Northwestern Wildcats","stats":{},"current":false},"ncaab.p.169880":{"name":"Gus Hurlburt","team":"Northwestern Wildcats","stats":{},"current":false},"ncaab.p.331213":{"name":"Jordan Clayton","team":"Northwestern Wildcats","stats":{},"current":false},"ncaab.p.331214":{"name":"Parker Strauss","team":"Northwestern Wildcats","stats":{},"current":false},"ncaab.p.331216":{"name":"Blake Barkley","team":"Northwestern Wildcats","stats":{},"current":false}}
